common_pygrpc/__init__.py
common_pygrpc/common_pb2.py
common_pygrpc/common_pb2_grpc.py
common_pygrpc/grpclib.py
common_pygrpc-1.0.2.dist-info/LICENSE
common_pygrpc-1.0.2.dist-info/METADATA
common_pygrpc-1.0.2.dist-info/WHEEL
common_pygrpc-1.0.2.dist-info/top_level.txt
common_pygrpc-1.0.2.dist-info/RECORD
