Metadata-Version: 2.1
Name: common-pygrpc
Version: 1.0.2
Summary: common python grpc service
Home-page: https://github.com/reggiepy/common_pygrpc
Author: reggiepy
Author-email: reggiepy@foxmail.com
License: LICENSE
Classifier: Programming Language :: Python :: 3
Classifier: License :: OSI Approved :: GNU Affero General Public License v3
Classifier: Operating System :: OS Independent
Requires-Python: >=3.6
License-File: LICENSE
Requires-Dist: grpcio (==1.50.0)
Requires-Dist: protobuf (==3.20.3)
